graycode/__init__.py
graycode/gray_code.py
graycode/gray_code_test.py
graycode-1.0.3.dist-info/DESCRIPTION.rst
graycode-1.0.3.dist-info/METADATA
graycode-1.0.3.dist-info/RECORD
graycode-1.0.3.dist-info/WHEEL
graycode-1.0.3.dist-info/metadata.json
graycode-1.0.3.dist-info/top_level.txt
