Metadata-Version: 2.0
Name: graycode
Version: 1.0.3
Summary: Convert two's complement integer to gray code and vice versa
Home-page: https://gitlab.com/heikkiorsila/gray-code
Author: Heikki Orsila
Author-email: heikki.orsila@iki.fi
License: UNKNOWN
Platform: UNKNOWN
Classifier: Programming Language :: Python :: 3
Classifier: License :: OSI Approved :: MIT License
Classifier: Operating System :: OS Independent
Requires-Python: >=3.5
